ipycrawl/__init__.py
ipycrawl/file.py
ipycrawl-0.0.2.dist-info/LICENSE
ipycrawl-0.0.2.dist-info/METADATA
ipycrawl-0.0.2.dist-info/WHEEL
ipycrawl-0.0.2.dist-info/top_level.txt
ipycrawl-0.0.2.dist-info/RECORD
